swagger_client/__init__.py
swagger_client/api_client.py
swagger_client/configuration.py
swagger_client/rest.py
swagger_client/api/__init__.py
swagger_client/api/commits_api.py
swagger_client/api/data_dumps_api.py
swagger_client/api/durations_api.py
swagger_client/api/external_durations_api.py
swagger_client/api/goals_api.py
swagger_client/api/heartbeats_api.py
swagger_client/api/insights_api.py
swagger_client/api/leaderboards_api.py
swagger_client/api/meta_api.py
swagger_client/api/organizations_api.py
swagger_client/api/projects_api.py
swagger_client/api/resources_api.py
swagger_client/api/stats_api.py
swagger_client/api/summaries_api.py
swagger_client/api/users_api.py
swagger_client/models/__init__.py
swagger_client/models/aggregate_daily_average.py
swagger_client/models/aggregate_stat_count.py
swagger_client/models/aggregate_stat_item.py
swagger_client/models/aggregate_stat_value.py
swagger_client/models/aggregate_stats.py
swagger_client/models/aggregate_total.py
swagger_client/models/all_time_since_today.py
swagger_client/models/branch_stat.py
swagger_client/models/bulk_delete_request.py
swagger_client/models/category_stat.py
swagger_client/models/city.py
swagger_client/models/commit.py
swagger_client/models/commit_detail_response.py
swagger_client/models/commits_list_response.py
swagger_client/models/cumulative_total.py
swagger_client/models/daily_average.py
swagger_client/models/data_dump.py
swagger_client/models/data_dump_request.py
swagger_client/models/dependency_stat.py
swagger_client/models/duration.py
swagger_client/models/durations_response.py
swagger_client/models/editor_resource.py
swagger_client/models/editor_stat.py
swagger_client/models/entity_stat.py
swagger_client/models/error.py
swagger_client/models/external_duration.py
swagger_client/models/external_duration_request.py
swagger_client/models/external_durations_response.py
swagger_client/models/goal.py
swagger_client/models/goal_chart_data.py
swagger_client/models/goal_detail_response.py
wakatime_api-0.1.3.dist-info/METADATA
wakatime_api-0.1.3.dist-info/WHEEL
wakatime_api-0.1.3.dist-info/top_level.txt
wakatime_api-0.1.3.dist-info/RECORD
