Metadata-Version: 2.4
Name: wakatime_api
Version: 0.1.3
Summary: REST API for accessing your WakaTime coding activity stats.
Home-page: https://github.com/EastArctica/wakatime-api-py
Author: East_Arctica
Author-email: eastarctica@gmail.com
Requires-Python: >=3.13
Requires-Dist: certifi>=14.5.14
Requires-Dist: python-dateutil>=2.5.3
Requires-Dist: setuptools>=21.0.0
Requires-Dist: six>=1.10
Requires-Dist: urllib3>=1.15.1
Dynamic: author
Dynamic: author-email
Dynamic: home-page
